{
    "id": 265311396,
    "ordertype": 0,
    "pin": false,
    "number": "581687929416418459",
    "customerid": 61672860,
    "customername": "ขายช่องทาง Tiktok",
    "customercode": "OTIK000000",
    "customeridnumber": "",
    "customeremail": "",
    "customerphone": "",
    "customeraddress": "",
    "customerpostcode": null,
    "customerprovince": null,
    "customerdistrict": null,
    "customersubdistrict": null,
    "customerstreetAddress": null,
    "customerbranchname": "",
    "customerbranchno": "",
    "facebookname": "",
    "facebookid": "",
    "line": "",
    "lineid": "",
    "reference": "",
    "reference2": "",
    "warehousecode": "W0001",
    "status": "Waiting",
    "paymentstatus": "Paid",
    "marketplacename": null,
    "marketplaceshippingstatus": null,
    "marketplacepayment": null,
    "amount": 180,
    "amount_pretax": 168.22,
    "vatamount": 11.78,
    "buyerAmount": 180.0,
    "shippingvat": 1,
    "shippingchannel": "J&T Express",
    "shippingamount_pretax": 0,
    "shippingamount_vat": 0,
    "shippingamount": 0,
    "shippingdate": "2025-12-17T13:00:00",
    "shippingdateString": "2025-12-17",
    "shippingname": "ส***ิง  ฟ***มุทร",
    "shippingaddress": "ไทย, ลำพูน, อำเภอเมืองลำพูน,น.*************************************************************************************************************************************************************************************************************** 51***",
    "shippingphone": "(+66)085*****09",
    "shippingemail": "",
    "shippingpostcode": "",
    "shippingprovince": "ลำพูน",
    "shippingdistrict": "เมืองลำพูน",
    "shippingsubdistrict": "",
    "shippingstreetAddress": "ไทย,, ,น.*************************************************************************************************************************************************************************************************************** 51***",
    "trackingno": "768064482124",
    "orderdate": "2025-12-16T22:16:03",
    "orderdateString": "2025-12-16",
    "paymentmethod": null,
    "paymentamount": 180,
    "paymentdate": null,
    "description": "",
    "discount": "",
    "platformdiscount_pretax": 0,
    "platformdiscount_vat": 0,
    "platformdiscount": 0,
    "sellerdiscount_pretax": 0,
    "sellerdiscount_vat": 0,
    "sellerdiscount": 0,
    "discountamount_pretax": 0,
    "discountamount_vat": 0,
    "discountamount": 0,
    "voucheramount_pretax": 0,
    "voucheramount_vat": 0,
    "voucheramount": 0,
    "shippingVoucher_pretax": 0,
    "shippingVoucher_vat": 0,
    "shippingVoucher": 0,
    "roundingAmount": 0.00,
    "vattype": 3,
    "saleschannel": "TIKTOK",
    "list": [
        {
            "id": 543885692,
            "productid": 22353551,
            "sku": "10014601001_PCS",
            "name": "FaThai ฟ้าไทย โฮม คิทเช่น ซอสผัดกะเพรา 40 กรัม (1 ซอง)",
            "number": 1,
            "unittext": "",
            "pricepernumber_pretax": 28.04,
            "pricepernumber_vat": 1.96,
            "pricepernumber": 30,
            "discount": "10",
            "discountPerNumber_pretax": 9.35,
            "discountPerNumber_vat": 0.65,
            "discountPerNumber": 10,
            "discountamount_pretax": 9.35,
            "discountamount_vat": 0.65,
            "discountamount": 10,
            "totalprice_pretax": 18.69,
            "totalprice_vat": 1.31,
            "totalprice": 20,
            "producttype": 0,
            "serialnolist": [],
            "expirylotlist": [],
            "skutype": null,
            "bundleid": null,
            "bundleitemid": null,
            "bundlenumber": null,
            "bundleCode": null,
            "bundleName": null,
            "integrationItemId": "1732721364021642819",
            "integrationVariantId": "1732721436522612291",
            "preOrder": false,
            "vat_status": 2
        },
        {
            "id": 543885693,
            "productid": 20337917,
            "sku": "10013121001_PCS",
            "name": "FaThai ฟ้าไทย โฮม คิทเช่น ซอสปรุงสำเร็จรูป 75 กรัม (ซอสรสพะโล้) 1 ซอง",
            "number": 2,
            "unittext": "",
            "pricepernumber_pretax": 28.04,
            "pricepernumber_vat": 1.96,
            "pricepernumber": 30,
            "discount": "10",
            "discountPerNumber_pretax": 9.35,
            "discountPerNumber_vat": 0.65,
            "discountPerNumber": 10,
            "discountamount_pretax": 18.69,
            "discountamount_vat": 1.31,
            "discountamount": 20,
            "totalprice_pretax": 37.38,
            "totalprice_vat": 2.62,
            "totalprice": 40,
            "producttype": 0,
            "serialnolist": [],
            "expirylotlist": [],
            "skutype": null,
            "bundleid": null,
            "bundleitemid": null,
            "bundlenumber": null,
            "bundleCode": null,
            "bundleName": null,
            "integrationItemId": "1732723500609865283",
            "integrationVariantId": "1732723483300169283",
            "preOrder": false,
            "vat_status": 2
        },
        {
            "id": 543885694,
            "productid": 17824243,
            "sku": "10011401005_PCS",
            "name": "FaThai ฟ้าไทย โฮม คิทเช่น ซอสปรุงสำเร็จรูป 75 กรัม (ซอสผัดผงกระหรี่) 1 ซอง",
            "number": 2,
            "unittext": "",
            "pricepernumber_pretax": 28.04,
            "pricepernumber_vat": 1.96,
            "pricepernumber": 30,
            "discount": "10",
            "discountPerNumber_pretax": 9.35,
            "discountPerNumber_vat": 0.65,
            "discountPerNumber": 10,
            "discountamount_pretax": 18.69,
            "discountamount_vat": 1.31,
            "discountamount": 20,
            "totalprice_pretax": 37.38,
            "totalprice_vat": 2.62,
            "totalprice": 40,
            "producttype": 0,
            "serialnolist": [],
            "expirylotlist": [],
            "skutype": null,
            "bundleid": null,
            "bundleitemid": null,
            "bundlenumber": null,
            "bundleCode": null,
            "bundleName": null,
            "integrationItemId": "1732727844905780803",
            "integrationVariantId": "1732727858980030019",
            "preOrder": false,
            "vat_status": 2
        },
        {
            "id": 543885695,
            "productid": 19793153,
            "sku": "10012601005_PCS",
            "name": "FaThai ฟ้าไทย โฮม คิทเช่น ซอสปรุงสำเร็จรูป 75 กรัม (ซอสรสต้มข่า) 1 ซอง",
            "number": 2,
            "unittext": "",
            "pricepernumber_pretax": 28.04,
            "pricepernumber_vat": 1.96,
            "pricepernumber": 30,
            "discount": "10",
            "discountPerNumber_pretax": 9.35,
            "discountPerNumber_vat": 0.65,
            "discountPerNumber": 10,
            "discountamount_pretax": 18.69,
            "discountamount_vat": 1.31,
            "discountamount": 20,
            "totalprice_pretax": 37.38,
            "totalprice_vat": 2.62,
            "totalprice": 40,
            "producttype": 0,
            "serialnolist": [],
            "expirylotlist": [],
            "skutype": null,
            "bundleid": null,
            "bundleitemid": null,
            "bundlenumber": null,
            "bundleCode": null,
            "bundleName": null,
            "integrationItemId": "1732727830624765507",
            "integrationVariantId": "1732727900721022531",
            "preOrder": false,
            "vat_status": 2
        },
        {
            "id": 543885696,
            "productid": 17824234,
            "sku": "10012501007_PCS",
            "name": "FaThai ฟ้าไทย โฮม คิทเช่น ซอสปรุงสำเร็จรูป 75 กรัม (ซอสแกงเขียวหวาน) 1 ซอง",
            "number": 2,
            "unittext": "",
            "pricepernumber_pretax": 28.04,
            "pricepernumber_vat": 1.96,
            "pricepernumber": 30,
            "discount": "10",
            "discountPerNumber_pretax": 9.35,
            "discountPerNumber_vat": 0.65,
            "discountPerNumber": 10,
            "discountamount_pretax": 18.69,
            "discountamount_vat": 1.31,
            "discountamount": 20,
            "totalprice_pretax": 37.38,
            "totalprice_vat": 2.62,
            "totalprice": 40,
            "producttype": 0,
            "serialnolist": [],
            "expirylotlist": [],
            "skutype": null,
            "bundleid": null,
            "bundleitemid": null,
            "bundlenumber": null,
            "bundleCode": null,
            "bundleName": null,
            "integrationItemId": "1732727866857719363",
            "integrationVariantId": "1732727910931793475",
            "preOrder": false,
            "vat_status": 2
        }
    ],
    "vatpercent": 7,
    "payments": [
        {
            "id": 311465047,
            "name": "Mbanking",
            "amount": 180,
            "paymentdatetime": "2025-12-16T22:16:19",
            "paymentdatetimeString": "2025-12-16 22:16",
            "paymentmethodid": 747640,
            "link": null,
            "verifySlip": null
        }
    ],
    "createdby": null,
    "createusername": null,
    "createuserid": 0,
    "sharelink": null,
    "isCOD": false,
    "tag": [],
    "createdatetime": "2025-12-16T22:16:06",
    "createdatetimeString": "2025-12-16 22:16",
    "updatedatetime": "2025-12-17T08:01:55",
    "updatedatetimeString": "2025-12-17 08:01",
    "expiredate": null,
    "expiredateString": null,
    "receivedate": null,
    "receivedateString": null,
    "successDate": null,
    "successDateString": null,
    "trackingList": [
        {
            "id": 0,
            "isMainTrackingNo": true,
            "trackingno": "768064482124",
            "trackingurl": "",
            "shippingdate": "2025-12-17T13:00:00",
            "shippingchannel": "J&T Express",
            "status": "Normal",
            "trackingProducts": null
        }
    ],
    "integrationName": "Tiktok Shop",
    "integrationShop": "7494160656861791811",
    "integrationCustomerId": "7494012480305267867",
    "integrationCustomer": "v4bEAUSAUNCXK45YNPPMGXA7J3Q2Y@scs2.tiktok.com",
    "integrationStatus": "112",
    "agent": null,
    "totalproductamount": 180,
    "uniquenumber": null,
    "currency": "THB",
    "properties": null,
    "isDeposit": false,
    "recentShipment": null,
    "returnOrders": null
}